mayawaves/__init__.py
mayawaves/coalescence.py
mayawaves/compactobject.py
mayawaves/radiation.py
mayawaves/utils/MAYAmetadata.pkl
mayawaves/utils/__init__.py
mayawaves/utils/catalogutils.py
mayawaves/utils/postnewtonianutils.py
mayawaves/utils/postprocessingutils.py
mayawaves-2025.12.dist-info/METADATA
mayawaves-2025.12.dist-info/WHEEL
mayawaves-2025.12.dist-info/licenses/LICENSE
mayawaves-2025.12.dist-info/RECORD
