Metadata-Version: 2.4
Name: mayawaves
Version: 2025.12
Summary: A python package for interacting with Einstein Toolkit simulations and the MAYA Catalog of NR Waveforms
Project-URL: Homepage, https://github.com/MayaWaves/mayawaves
Project-URL: Bug Tracker, https://github.com/MayaWaves/mayawaves/issues
Author: Surendra Anne, Miguel Gracia-Linares, Hector Iglesias, Aasim Jan, Erick Martinez, Lu Lu, Filippo Meoni, Ryan Nowicki, Max L. Trostel, Bing-Jyun Tsao, Finny Valorz
Author-email: Deborah Ferguson <deborah.l.ferguson@gmail.com>
License:                     GNU GENERAL PUBLIC LICENSE
License-File: LICENSE
Classifier: License :: OSI Approved :: GNU General Public License v3 (GPLv3)
Classifier: Operating System :: OS Independent
Classifier: Programming Language :: Python :: 3
Requires-Python: >=3.8
Requires-Dist: freezegun
Requires-Dist: matplotlib
Requires-Dist: mock
Requires-Dist: numba
Requires-Dist: numpy
Requires-Dist: pandas
Requires-Dist: romspline
Requires-Dist: scipy
Requires-Dist: scri
Requires-Dist: wget
